segmentIdentifier/__init__.py
segmentIdentifier/run.py
segmentIdentifier/brace_remover/__init__.py
segmentIdentifier/brace_remover/removeBraces.py
segmentIdentifier/ncec/__init__.py
segmentIdentifier/ncec/config.py
segmentIdentifier/ncec/dotGenerator.py
segmentIdentifier/ncec/esc.py
segmentIdentifier/ncec/generateParameters.py
segmentIdentifier/ncec/graph.py
segmentIdentifier/ncec/main.py
segmentIdentifier/ncec/metric.py
segmentIdentifier/ncec/ncec.py
segmentIdentifier/ncec/output.py
segmentIdentifier/ncec/populateVHash.py
segmentIdentifier/ncec/precomputation.py
segmentIdentifier/ncec/sddc.py
segmentIdentifier/ncec/sdgExtractor.py
segmentIdentifier/ncec/segmentation.py
segmentIdentifier-1.0.1.dist-info/DESCRIPTION.rst
segmentIdentifier-1.0.1.dist-info/METADATA
segmentIdentifier-1.0.1.dist-info/RECORD
segmentIdentifier-1.0.1.dist-info/WHEEL
segmentIdentifier-1.0.1.dist-info/metadata.json
segmentIdentifier-1.0.1.dist-info/top_level.txt
segmentRefactor/__init__.py
segmentRefactor/run.py
segmentRefactor/brace_remover/__init__.py
segmentRefactor/brace_remover/removeBraces.py
segmentRefactor/ncec/__init__.py
segmentRefactor/ncec/config.py
segmentRefactor/ncec/dotGenerator.py
segmentRefactor/ncec/esc.py
segmentRefactor/ncec/generateParameters.py
segmentRefactor/ncec/graph.py
segmentRefactor/ncec/graph_3.py
segmentRefactor/ncec/main.py
segmentRefactor/ncec/metric.py
segmentRefactor/ncec/metric_3.py
segmentRefactor/ncec/ncec.py
segmentRefactor/ncec/ncec_3.py
segmentRefactor/ncec/output.py
segmentRefactor/ncec/populateVHash.py
segmentRefactor/ncec/precomputation.py
segmentRefactor/ncec/sddc.py
segmentRefactor/ncec/sdgExtractor.py
segmentRefactor/ncec/segmentation.py
